purecpp_meta_t/RagPUREAI_meta.cpython-311-x86_64-linux-gnu.so
purecpp_meta_t/__init__.py
purecpp_meta_t/libprotobuf.so
purecpp_meta_t/libprotobuf.so.25
purecpp_meta_t/libprotoc.so
purecpp_meta_t/libprotoc.so.25
purecpp_meta_t-1.0.11.dist-info/METADATA
purecpp_meta_t-1.0.11.dist-info/WHEEL
purecpp_meta_t-1.0.11.dist-info/top_level.txt
purecpp_meta_t-1.0.11.dist-info/RECORD
