Metadata-Version: 2.2
Name: purecpp_meta_t
Version: 1.0.11
Summary: Metadata capture in chunks for hybrid search. This package is a part of the PureCPP ecosystem. Beta version.
Home-page: https://github.com/pureai-ecosystem/purecpp
Author: Diogo Vieira
Author-email: contato@pureai.com.br
Classifier: Programming Language :: Python :: 3
Classifier: Operating System :: POSIX :: Linux
Requires-Dist: purecpp_libs
Requires-Dist: auditwheel
Requires-Dist: build
Requires-Dist: requests
Requires-Dist: wheel
Requires-Dist: pybind11
Requires-Dist: setuptools
Dynamic: author
Dynamic: author-email
Dynamic: classifier
Dynamic: home-page
Dynamic: requires-dist
Dynamic: summary
